Metadata-Version: 1.0
Name: selection-sort
Version: 0.0.4
Summary: My package description
Home-page: UNKNOWN
Author: Jiro1703
Author-email: absurd4657@mail.ru
License: UNKNOWN
Platform: UNKNOWN
